vividict/__init__.py
vividict/vividict.py
vividict-0.1.1.dist-info/METADATA
vividict-0.1.1.dist-info/WHEEL
vividict-0.1.1.dist-info/licenses/LICENSE
vividict-0.1.1.dist-info/RECORD
