Metadata-Version: 2.3
Name: vividict
Version: 0.1.1
Summary: Package containing the Vividict class. Allows for nested dictionaries.
Project-URL: Homepage, https://stockscrapers.com
Project-URL: Repository, https://github.com/StockScrapers/vividict
Project-URL: Bug Tracker, https://github.com/StockScrapers/vividict/issues
Project-URL: Changelog, https://github.com/me/vividict/blob/master/CHANGELOG.md
Author-email: Charbel Marche <charbelmarche33@gmail.com>
Maintainer-email: Charbel Marche <charbelmarche33@gmail.com>
License: MIT License
License-File: LICENSE
Keywords: nested dictionary,vividict
Classifier: Development Status :: 4 - Beta
Classifier: Programming Language :: Python
Requires-Python: >=3.12
